vita_module/__init__.py
vita_module/vita_module.py
vita_module-1.0.0.dist-info/licenses/LICENSE.md
vita_module-1.0.0.dist-info/METADATA
vita_module-1.0.0.dist-info/WHEEL
vita_module-1.0.0.dist-info/top_level.txt
vita_module-1.0.0.dist-info/RECORD
