Metadata-Version: 2.4
Name: vita_module
Version: 1.0.0
Summary: a library to parse playstation vita prx and velf
Author: olebeck
Project-URL: Homepage, https://github.com/olebeck/vita_module
Classifier: License :: OSI Approved :: MIT License
Classifier: Operating System :: OS Independent
Requires-Python: >=3.11
License-File: LICENSE.md
Dynamic: license-file
